guidera/__init__.py
guidera/client.py
guidera/test_spinner.py
guidera-0.1.10.dist-info/METADATA
guidera-0.1.10.dist-info/WHEEL
guidera-0.1.10.dist-info/RECORD
