Metadata-Version: 2.3
Name: guidera
Version: 0.1.10
Summary: Client application for Tilantra API
Author: Your Name
Author-email: your.email@example.com
Requires-Python: >=3.9,<4.0
Classifier: Programming Language :: Python :: 3
Classifier: Programming Language :: Python :: 3.9
Classifier: Programming Language :: Python :: 3.10
Classifier: Programming Language :: Python :: 3.11
Classifier: Programming Language :: Python :: 3.12
Classifier: Programming Language :: Python :: 3.13
Requires-Dist: PyJWT (>=2.8.0,<3.0.0)
Requires-Dist: fastapi (>=0.104.0,<0.105.0)
Requires-Dist: httpx (>=0.25.0,<0.26.0)
Requires-Dist: passlib[bcrypt] (>=1.7.4,<2.0.0)
Requires-Dist: pydantic (>=2.4.2,<3.0.0)
Requires-Dist: python-jose[cryptography] (>=3.3.0,<4.0.0)
Requires-Dist: python-multipart (>=0.0.6,<0.0.7)
Requires-Dist: redis (>=5.0.1,<6.0.0)
Requires-Dist: requests (>=2.0.0,<3.0.0)
Requires-Dist: uvicorn (>=0.24.0,<0.25.0)
Requires-Dist: yaspin
